ExcelSheetsToPDF/__init__.py
ExcelSheetsToPDF_pkg_unpac-0.1.0.dist-info/METADATA
ExcelSheetsToPDF_pkg_unpac-0.1.0.dist-info/WHEEL
ExcelSheetsToPDF_pkg_unpac-0.1.0.dist-info/top_level.txt
ExcelSheetsToPDF_pkg_unpac-0.1.0.dist-info/RECORD
