Metadata-Version: 2.1
Name: ExcelSheetsToPDF-pkg-unpac
Version: 0.1.0
Summary: transform excel file sheets save each pdf file
Home-page: https://github.com/apeony/ExcelSheetstoPDF
Author: YEONJU JUNG
Author-email: unpac.tech@gmail.com
License: UNKNOWN
Platform: UNKNOWN
Classifier: Programming Language :: Python :: 3
Classifier: License :: OSI Approved :: MIT License
Classifier: Operating System :: OS Independent
Requires-Python: >=3.9
